LICENSE
MANIFEST.in
setup.py
tests.py
docs/Makefile
docs/conf.py
docs/index.rst
docs/make.bat
docs/_static/flask-script.png
docs/_static/index.html
docs/_themes/README
docs/_themes/flask_theme_support.py
docs/_themes/flask/theme.conf
docs/_themes/flask/static/flasky.css_t
docs/_themes/flask_small/layout.html
docs/_themes/flask_small/theme.conf
docs/_themes/flask_small/static/flasky.css_t
simplecli/__init__.py
simplecli/cli.py
simplecli/commands.py
simplecli.egg-info/PKG-INFO
simplecli.egg-info/SOURCES.txt
simplecli.egg-info/dependency_links.txt
simplecli.egg-info/not-zip-safe
simplecli.egg-info/top_level.txt