Metadata-Version: 1.1
Name: simplecli
Version: 0.1.0
Summary: Makes writing command line interfaces simple
Home-page: http://github.com/baeuml/simplecli
Author: Dan Jacob, Sean Lynch, Martin Baeuml
Author-email: danjac354@gmail.com, techniq35@gmail.com, baeuml@gmail.com
License: BSD
Platform: any
Classifier: Development Status :: 4 - Beta
Classifier: Environment :: Console
Classifier: Intended Audience :: Developers
Classifier: License :: OSI Approved :: BSD License
Classifier: Operating System :: OS Independent
Classifier: Programming Language :: Python
Classifier: Topic :: Software Development :: Libraries :: Python Modules
